AUTHORS.rst
CHANGELOG.rst
LICENSE
MANIFEST.in
README.rst
setup.py
django_simple_autocomplete.egg-info/PKG-INFO
django_simple_autocomplete.egg-info/SOURCES.txt
django_simple_autocomplete.egg-info/dependency_links.txt
django_simple_autocomplete.egg-info/not-zip-safe
django_simple_autocomplete.egg-info/requires.txt
django_simple_autocomplete.egg-info/top_level.txt
simple_autocomplete/__init__.py
simple_autocomplete/__init__.pyc
simple_autocomplete/models.py
simple_autocomplete/models.pyc
simple_autocomplete/monkey.py
simple_autocomplete/monkey.pyc
simple_autocomplete/urls.py
simple_autocomplete/urls.pyc
simple_autocomplete/utils.py
simple_autocomplete/utils.pyc
simple_autocomplete/views.py
simple_autocomplete/views.pyc
simple_autocomplete/widgets.py
simple_autocomplete/widgets.pyc
simple_autocomplete/static/simple_autocomplete/jquery-ui.css
simple_autocomplete/static/simple_autocomplete/jquery-ui.js
simple_autocomplete/tests/__init__.py
simple_autocomplete/tests/manage.py
simple_autocomplete/tests/models.py
simple_autocomplete/tests/test_it.py
simple_autocomplete/tests/urls.py
simple_autocomplete/tests/requirements/19.txt
simple_autocomplete/tests/settings/19.py
simple_autocomplete/tests/settings/__init__.py