Metadata-Version: 1.1
Name: django-simple-autocomplete
Version: 1.9.1
Summary: App enabling the use of jQuery UI autocomplete widget for ModelChoiceFields with minimal configuration required.
Home-page: http://github.com/praekelt/django-simple-autocomplete
Author: Praekelt Consulting
Author-email: dev@praekelt.com
License: BSD
Platform: UNKNOWN
Classifier: Programming Language :: Python
Classifier: License :: OSI Approved :: BSD License
Classifier: Operating System :: OS Independent
Classifier: Framework :: Django
Classifier: Intended Audience :: Developers
Classifier: Topic :: Internet :: WWW/HTTP :: Dynamic Content
